simp_tools
