Metadata-Version: 1.0
Name: simp-tools
Version: 0.1.1.2
Summary: Simple tools for sharing between repos
Home-page: https://github.com/dsimpson1980/simp_tools.git
Author: Dave Simpson
Author-email: davesimpson1980@gmail.com
License: MIT
Platform: UNKNOWN
